gym_bullet_chess/__init__.py
gym_bullet_chess/assets/bB.png
gym_bullet_chess/assets/bK.png
gym_bullet_chess/assets/bN.png
gym_bullet_chess/assets/bP.png
gym_bullet_chess/assets/bQ.png
gym_bullet_chess/assets/bR.png
gym_bullet_chess/assets/wB.png
gym_bullet_chess/assets/wK.png
gym_bullet_chess/assets/wN.png
gym_bullet_chess/assets/wP.png
gym_bullet_chess/assets/wQ.png
gym_bullet_chess/assets/wR.png
gym_bullet_chess/envs/__init__.py
gym_bullet_chess/envs/bullet_chess_env.py
gym_bullet_chess/utils/__init__.py
gym_bullet_chess/utils/encoding.py
gym_bullet_chess/wrappers/__init__.py
gym_bullet_chess/wrappers/real_time.py
gym_bullet_chess-0.0.1.dist-info/licenses/LICENSE
tests/__init__.py
tests/test_bullet_env.py
tests/test_real_time.py
gym_bullet_chess-0.0.1.dist-info/METADATA
gym_bullet_chess-0.0.1.dist-info/WHEEL
gym_bullet_chess-0.0.1.dist-info/top_level.txt
gym_bullet_chess-0.0.1.dist-info/RECORD
