Metadata-Version: 2.4
Name: gym_bullet_chess
Version: 0.0.1
Summary: Gymnasium-compatible bullet chess environment with real-time constraints.
Home-page: https://github.com/ChoiCube84/gym-bullet-chess
Author: ChoiCube84
Author-email: wldnd0804@gmail.com
License: GPL-3.0-or-later
Project-URL: Source, https://github.com/ChoiCube84/gym-bullet-chess
Project-URL: Issues, https://github.com/ChoiCube84/gym-bullet-chess/issues
Keywords: gymnasium reinforcement-learning chess bullet
Classifier: Development Status :: 3 - Alpha
Classifier: Intended Audience :: Science/Research
Classifier: License :: OSI Approved :: GNU General Public License v3 (GPLv3)
Classifier: Programming Language :: Python :: 3
Classifier: Programming Language :: Python :: 3 :: Only
Classifier: Programming Language :: Python :: 3.8
Classifier: Programming Language :: Python :: 3.9
Classifier: Programming Language :: Python :: 3.10
Classifier: Programming Language :: Python :: 3.11
Classifier: Programming Language :: Python :: 3.12
Classifier: Topic :: Games/Entertainment :: Board Games
Classifier: Topic :: Scientific/Engineering :: Artificial Intelligence
Requires-Python: >=3.8
License-File: LICENSE
Requires-Dist: gymnasium>=1.0.0
Requires-Dist: chess>=1.10.0
Requires-Dist: numpy>=1.24.0
Provides-Extra: gui
Requires-Dist: pygame; extra == "gui"
Provides-Extra: render
Requires-Dist: Pillow; extra == "render"
Dynamic: author
Dynamic: author-email
Dynamic: classifier
Dynamic: description
Dynamic: description-content-type
Dynamic: home-page
Dynamic: keywords
Dynamic: license
Dynamic: license-file
Dynamic: project-url
Dynamic: provides-extra
Dynamic: requires-dist
Dynamic: requires-python
Dynamic: summary
